wayward/__init__.py
wayward/logsum.py
wayward/parsimonious.py
wayward/py.typed
wayward/significant_words.py
wayward/specific_term_estimators.py
wayward-0.3.2.dist-info/LICENSE
wayward-0.3.2.dist-info/WHEEL
wayward-0.3.2.dist-info/METADATA
wayward-0.3.2.dist-info/RECORD
